bislackbot/__init__.py
bislackbot/slackbot.py
bislackbot-0.1.3.dist-info/METADATA
bislackbot-0.1.3.dist-info/WHEEL
bislackbot-0.1.3.dist-info/top_level.txt
bislackbot-0.1.3.dist-info/RECORD
