Metadata-Version: 2.1
Name: bislackbot
Version: 0.1.3
Summary: bislackbot for automation sending report
Home-page: https://github.com/bahanh/bislackbot
Author: hanbnb6@onemount.com
Author-email: hanbnb6@onemount.com
License: MIT
Platform: UNKNOWN
Classifier: License :: OSI Approved :: MIT License
Classifier: Programming Language :: Python :: 3.7
Classifier: Programming Language :: Python :: 3.8
Requires-Dist: pandas
Requires-Dist: numpy
